{"users":[{"id":876328173297954800,"id_str":"876328173297954820","name":"Roger Federer Fdn","screen_name":"rogerfedererfdn","location":"Zurich, Switzerland","url":"http://www.rogerfedererfoundation.org","description":"Welcome to the official Roger Federer Foundation Twitter account. You will find information about our work and related topics.#rogerfederer #educationempowers","protected":false,"followers_count":21493,"friends_count":151,"listed_count":44,"created_at":"Sun Jun 18 06:38:12 +0000 2017","favourites_count":126,"utc_offset":7200,"time_zone":"Bern","geo_enabled":false,"verified":true,"statuses_count":194,"lang":"en","contributors_enabled":false,"is_translator":false,"is_translation_enabled":false,"profile_background_color":"F5F8FA","profile_background_image_url":null,"profile_background_image_url_https":null,"profile_background_tile":false,"profile_image_url":"http://pbs.twimg.com/profile_images/876330581784764417/vPVWMGt0_normal.jpg","profile_image_url_https":"https://pbs.twimg.com/profile_images/876330581784764417/vPVWMGt0_normal.jpg","profile_banner_url":"https://pbs.twimg.com/profile_banners/876328173297954820/1497768663","profile_link_color":"1DA1F2","profile_sidebar_border_color":"C0DEED","profile_sidebar_fill_color":"DDEEF6","profile_text_color":"333333","profile_use_background_image":true,"has_extended_profile":true,"default_profile":true,"default_profile_image":false,"following":null,"follow_request_sent":null,"notifications":null,"muting":null,"blocking":null,"blocked_by":null,"translator_type":"none"},{"id":937499232,"id_str":"937499232","name":"Malala","screen_name":"Malala","location":"","url":"http://malala.org","description":"20 years old | advocate for girls’ education and women's equality | UN Messenger of Peace | founder @MalalaFund","protected":false,"followers_count":1203177,"friends_count":188,"listed_count":2775,"created_at":"Fri Nov 09 18:34:52 +0000 2012","favourites_count":769,"utc_offset":-14400,"time_zone":"Eastern Time (US & Canada)","geo_enabled":false,"verified":true,"statuses_count":275,"lang":"en","contributors_enabled":false,"is_translator":false,"is_translation_enabled":false,"profile_background_color":"000000","profile_background_image_url":"http://abs.twimg.com/images/themes/theme1/bg.png","profile_background_image_url_https":"https://abs.twimg.com/images/themes/theme1/bg.png","profile_background_tile":false,"profile_image_url":"http://pbs.twimg.com/profile_images/972091218883526656/ElSdbAsZ_normal.jpg","profile_image_url_https":"https://pbs.twimg.com/profile_images/972091218883526656/ElSdbAsZ_normal.jpg","profile_banner_url":"https://pbs.twimg.com/profile_banners/937499232/1522520075","profile_link_color":"E0005B","profile_sidebar_border_color":"000000","profile_sidebar_fill_color":"000000","profile_text_color":"000000","profile_use_background_image":false,"has_extended_profile":false,"default_profile":false,"default_profile_image":false,"following":null,"follow_request_sent":null,"notifications":null,"muting":null,"blocking":null,"blocked_by":null,"translator_type":"none"},{"id":393458111,"id_str":"393458111","name":"Stacey Childress","screen_name":"NextGenStacey","location":"","url":null,"description":"CEO of NewSchools Venture Fund, investing in people and ideas with potential to accelerate learning and expand opportunities for low-income young people","protected":false,"followers_count":12414,"friends_count":1719,"listed_count":293,"created_at":"Tue Oct 18 15:27:44 +0000 2011","favourites_count":469,"utc_offset":null,"time_zone":null,"geo_enabled":false,"verified":false,"statuses_count":2868,"lang":"en","contributors_enabled":false,"is_translator":false,"is_translation_enabled":false,"profile_background_color":"EBEBEB","profile_background_image_url":"http://abs.twimg.com/images/themes/theme7/bg.gif","profile_background_image_url_https":"https://abs.twimg.com/images/themes/theme7/bg.gif","profile_background_tile":false,"profile_image_url":"http://pbs.twimg.com/profile_images/1886351977/stacey_normal.jpg","profile_image_url_https":"https://pbs.twimg.com/profile_images/1886351977/stacey_normal.jpg","profile_banner_url":"https://pbs.twimg.com/profile_banners/393458111/1402584500","profile_link_color":"69608A","profile_sidebar_border_color":"DFDFDF","profile_sidebar_fill_color":"F3F3F3","profile_text_color":"333333","profile_use_background_image":true,"has_extended_profile":false,"default_profile":false,"default_profile_image":false,"following":null,"follow_request_sent":null,"notifications":null,"muting":null,"blocking":null,"blocked_by":null,"translator_type":"none"},{"id":99008565,"id_str":"99008565","name":"孫正義","screen_name":"masason","location":"","url":"http://www.softbank.co.jp/","description":"孫正義です。 Twitterで多くの皆さんと時空を超えて、心の繋がりが広がっていく事に感動しています。初めてInternetに出会った時以来の感動です。世界が平和でより多くの人々が、幸福になれる事を心から願っています。","protected":false,"followers_count":2473977,"friends_count":80,"listed_count":58104,"created_at":"Thu Dec 24 02:26:24 +0000 2009","favourites_count":94,"utc_offset":32400,"time_zone":"Tokyo","geo_enabled":false,"verified":true,"statuses_count":5979,"lang":"ja","contributors_enabled":false,"is_translator":false,"is_translation_enabled":false,"profile_background_color":"C0DEED","profile_background_image_url":"http://abs.twimg.com/images/themes/theme1/bg.png","profile_background_image_url_https":"https://abs.twimg.com/images/themes/theme1/bg.png","profile_background_tile":false,"profile_image_url":"http://pbs.twimg.com/profile_images/2579542348/l2b371d8r57tu6m4wu7i_normal.jpeg","profile_image_url_https":"https://pbs.twimg.com/profile_images/2579542348/l2b371d8r57tu6m4wu7i_normal.jpeg","profile_link_color":"1DA1F2","profile_sidebar_border_color":"C0DEED","profile_sidebar_fill_color":"DDEEF6","profile_text_color":"333333","profile_use_background_image":true,"has_extended_profile":false,"default_profile":true,"default_profile_image":false,"following":null,"follow_request_sent":null,"notifications":null,"muting":null,"blocking":null,"blocked_by":null,"translator_type":"none"},{"id":811377,"id_str":"811377","name":"Reddit","screen_name":"reddit","location":"San Francisco, CA","url":"http://reddit.com","description":"The front page of the internet • Get the app: http://reddit.com/mobile/download • Interested in doing an AMA? E-mail ama@reddit.com","protected":false,"followers_count":549172,"friends_count":879,"listed_count":7049,"created_at":"Mon Mar 05 03:38:33 +0000 2007","favourites_count":7752,"utc_offset":-25200,"time_zone":"Pacific Time (US & Canada)","geo_enabled":true,"verified":true,"statuses_count":85912,"lang":"en","contributors_enabled":false,"is_translator":false,"is_translation_enabled":false,"profile_background_color":"022330","profile_background_image_url":"http://pbs.twimg.com/profile_background_images/562126199443304448/Gjg2KVpa.png","profile_background_image_url_https":"https://pbs.twimg.com/profile_background_images/562126199443304448/Gjg2KVpa.png","profile_background_tile":true,"profile_image_url":"http://pbs.twimg.com/profile_images/868147475852312577/fjCSPU-a_normal.jpg","profile_image_url_https":"https://pbs.twimg.com/profile_images/868147475852312577/fjCSPU-a_normal.jpg","profile_banner_url":"https://pbs.twimg.com/profile_banners/811377/1513715463","profile_link_color":"0084B4","profile_sidebar_border_color":"181A1E","profile_sidebar_fill_color":"252429","profile_text_color":"666666","profile_use_background_image":true,"has_extended_profile":false,"default_profile":false,"default_profile_image":false,"following":null,"follow_request_sent":null,"notifications":null,"muting":null,"blocking":null,"blocked_by":null,"translator_type":"none"},{"id":747807250819981300,"id_str":"747807250819981312","name":"Theresa May","screen_name":"theresa_may","location":"","url":null,"description":"Prime Minister and @Conservatives Leader.","protected":false,"followers_count":503191,"friends_count":14,"listed_count":3532,"created_at":"Tue Jun 28 15:01:57 +0000 2016","favourites_count":33,"utc_offset":-25200,"time_zone":"Pacific Time (US & Canada)","geo_enabled":false,"verified":true,"statuses_count":741,"lang":"en-gb","contributors_enabled":false,"is_translator":false,"is_translation_enabled":false,"profile_background_color":"F5F8FA","profile_background_image_url":null,"profile_background_image_url_https":null,"profile_background_tile":false,"profile_image_url":"http://pbs.twimg.com/profile_images/936639677121081344/_e5l_DEG_normal.jpg","profile_image_url_https":"https://pbs.twimg.com/profile_images/936639677121081344/_e5l_DEG_normal.jpg","profile_banner_url":"https://pbs.twimg.com/profile_banners/747807250819981312/1514890542","profile_link_color":"1DA1F2","profile_sidebar_border_color":"C0DEED","profile_sidebar_fill_color":"DDEEF6","profile_text_color":"333333","profile_use_background_image":true,"has_extended_profile":false,"default_profile":true,"default_profile_image":false,"following":null,"follow_request_sent":null,"notifications":null,"muting":null,"blocking":null,"blocked_by":null,"translator_type":"none"},{"id":1732829419,"id_str":"1732829419","name":"Elizabeth Kolbert","screen_name":"ElizKolbert","location":"","url":"http://ElizabethKolbert.com","description":"I am a New Yorker staff writer and author of Field Notes from a Catastrophe and The Sixth Extinction.","protected":false,"followers_count":30987,"friends_count":523,"listed_count":1000,"created_at":"Thu Sep 05 18:56:14 +0000 2013","favourites_count":860,"utc_offset":-10800,"time_zone":"Atlantic Time (Canada)","geo_enabled":false,"verified":true,"statuses_count":1481,"lang":"en","contributors_enabled":false,"is_translator":false,"is_translation_enabled":false,"profile_background_color":"FFFFFF","profile_background_image_url":"http://pbs.twimg.com/profile_background_images/378800000169323858/x5yg-byU.png","profile_background_image_url_https":"https://pbs.twimg.com/profile_background_images/378800000169323858/x5yg-byU.png","profile_background_tile":false,"profile_image_url":"http://pbs.twimg.com/profile_images/497547880505163776/JPBq4RWA_normal.jpeg","profile_image_url_https":"https://pbs.twimg.com/profile_images/497547880505163776/JPBq4RWA_normal.jpeg","profile_banner_url":"https://pbs.twimg.com/profile_banners/1732829419/1389896523","profile_link_color":"0084B4","profile_sidebar_border_color":"FFFFFF","profile_sidebar_fill_color":"DDEEF6","profile_text_color":"333333","profile_use_background_image":true,"has_extended_profile":true,"default_profile":false,"default_profile_image":false,"following":null,"follow_request_sent":null,"notifications":null,"muting":null,"blocking":null,"blocked_by":null,"translator_type":"none"},{"id":14260960,"id_str":"14260960","name":"Justin Trudeau","screen_name":"JustinTrudeau","location":"Papineau","url":"http://pm.gc.ca","description":"Account run by the 23rd Prime Minister of Canada and staff… Compte géré par le 23e premier ministre du Canada et personnel.","protected":false,"followers_count":4092551,"friends_count":965,"listed_count":12135,"created_at":"Sun Mar 30 21:04:14 +0000 2008","favourites_count":66,"utc_offset":-14400,"time_zone":"Eastern Time (US & Canada)","geo_enabled":true,"verified":true,"statuses_count":18090,"lang":"en","contributors_enabled":false,"is_translator":false,"is_translation_enabled":false,"profile_background_color":"DBDCDD","profile_background_image_url":"http://pbs.twimg.com/profile_background_images/538085032842113025/cK69w4mC.png","profile_background_image_url_https":"https://pbs.twimg.com/profile_background_images/538085032842113025/cK69w4mC.png","profile_background_tile":false,"profile_image_url":"http://pbs.twimg.com/profile_images/950393608221454336/NbB_X0TG_normal.jpg","profile_image_url_https":"https://pbs.twimg.com/profile_images/950393608221454336/NbB_X0TG_normal.jpg","profile_banner_url":"https://pbs.twimg.com/profile_banners/14260960/1499699762","profile_link_color":"B50000","profile_sidebar_border_color":"FFFFFF","profile_sidebar_fill_color":"B80B0B","profile_text_color":"000000","profile_use_background_image":false,"has_extended_profile":false,"default_profile":false,"default_profile_image":false,"following":null,"follow_request_sent":null,"notifications":null,"muting":null,"blocking":null,"blocked_by":null,"translator_type":"none"},{"id":20551702,"id_str":"20551702","name":"Jacqueline Novogratz","screen_name":"jnovogratz","location":"New York, NY (sometimes)","url":"http://www.acumen.org","description":"Founder/CEO of @acumen to find solutions to poverty & build dignity. Author of The Blue Sweater, lover of poetry, believer in possibility.","protected":false,"followers_count":536749,"friends_count":381,"listed_count":3935,"created_at":"Tue Feb 10 22:14:06 +0000 2009","favourites_count":1478,"utc_offset":-14400,"time_zone":"Eastern Time (US & Canada)","geo_enabled":true,"verified":true,"statuses_count":6505,"lang":"en","contributors_enabled":false,"is_translator":false,"is_translation_enabled":false,"profile_background_color":"FAF5F5","profile_background_image_url":"http://pbs.twimg.com/profile_background_images/448850841735143425/NjfHzDsd.jpeg","profile_background_image_url_https":"https://pbs.twimg.com/profile_background_images/448850841735143425/NjfHzDsd.jpeg","profile_background_tile":false,"profile_image_url":"http://pbs.twimg.com/profile_images/783377876242599936/3UhlSL1G_normal.jpg","profile_image_url_https":"https://pbs.twimg.com/profile_images/783377876242599936/3UhlSL1G_normal.jpg","profile_banner_url":"https://pbs.twimg.com/profile_banners/20551702/1427753961","profile_link_color":"1B95E0","profile_sidebar_border_color":"FFFFFF","profile_sidebar_fill_color":"99CC33","profile_text_color":"3E4415","profile_use_background_image":true,"has_extended_profile":false,"default_profile":false,"default_profile_image":false,"following":null,"follow_request_sent":null,"notifications":null,"muting":null,"blocking":null,"blocked_by":null,"translator_type":"none"},{"id":277434037,"id_str":"277434037","name":"Ratan N. Tata","screen_name":"RNTata2000","location":"Mumbai","url":null,"description":"Chairman Emeritus of Tata Sons. Chairman of Tata Trusts. Personal interests - aviation, automobiles, scuba diving and architectural design.","protected":false,"followers_count":7001874,"friends_count":41,"listed_count":3086,"created_at":"Tue Apr 05 11:01:00 +0000 2011","favourites_count":10,"utc_offset":19800,"time_zone":"Mumbai","geo_enabled":true,"verified":true,"statuses_count":137,"lang":"en","contributors_enabled":false,"is_translator":false,"is_translation_enabled":false,"profile_background_color":"C0DEED","profile_background_image_url":"http://abs.twimg.com/images/themes/theme1/bg.png","profile_background_image_url_https":"https://abs.twimg.com/images/themes/theme1/bg.png","profile_background_tile":false,"profile_image_url":"http://pbs.twimg.com/profile_images/1655289586/RNT-Image_01_normal.jpg","profile_image_url_https":"https://pbs.twimg.com/profile_images/1655289586/RNT-Image_01_normal.jpg","profile_link_color":"1DA1F2","profile_sidebar_border_color":"C0DEED","profile_sidebar_fill_color":"DDEEF6","profile_text_color":"333333","profile_use_background_image":true,"has_extended_profile":false,"default_profile":true,"default_profile_image":false,"following":null,"follow_request_sent":null,"notifications":null,"muting":null,"blocking":null,"blocked_by":null,"translator_type":"none"},{"id":305588032,"id_str":"305588032","name":"Wendy Kopp","screen_name":"wendykopp","location":"New York, New York","url":"http://www.teachforall.org","description":"CEO of @TeachForAll and founder of @TeachForAmerica.  Mom of four great kids and wife of great guy.","protected":false,"followers_count":35024,"friends_count":500,"listed_count":0,"created_at":"Thu May 26 13:38:35 +0000 2011","favourites_count":596,"utc_offset":-14400,"time_zone":"Eastern Time (US & Canada)","geo_enabled":true,"verified":true,"statuses_count":4389,"lang":"en","contributors_enabled":false,"is_translator":false,"is_translation_enabled":false,"profile_background_color":"C0DEED","profile_background_image_url":"http://pbs.twimg.com/profile_background_images/693205709/02116492ffd0d15bd10433eb5da7874f.jpeg","profile_background_image_url_https":"https://pbs.twimg.com/profile_background_images/693205709/02116492ffd0d15bd10433eb5da7874f.jpeg","profile_background_tile":true,"profile_image_url":"http://pbs.twimg.com/profile_images/805826310371213312/yKgntyFe_normal.jpg","profile_image_url_https":"https://pbs.twimg.com/profile_images/805826310371213312/yKgntyFe_normal.jpg","profile_banner_url":"https://pbs.twimg.com/profile_banners/305588032/1471626669","profile_link_color":"0084B4","profile_sidebar_border_color":"FFFFFF","profile_sidebar_fill_color":"DDEEF6","profile_text_color":"333333","profile_use_background_image":true,"has_extended_profile":false,"default_profile":false,"default_profile_image":false,"following":null,"follow_request_sent":null,"notifications":null,"muting":null,"blocking":null,"blocked_by":null,"translator_type":"none"},{"id":27247847,"id_str":"27247847","name":"NewSchools","screen_name":"nsvf","location":"Oakland, CA","url":"http://www.newschools.org","description":"NewSchools is a nonprofit venture philanthropy working to reimagine public education so that all children have the opportunity to succeed","protected":false,"followers_count":29736,"friends_count":1140,"listed_count":846,"created_at":"Sat Mar 28 15:34:04 +0000 2009","favourites_count":444,"utc_offset":-25200,"time_zone":"Pacific Time (US & Canada)","geo_enabled":true,"verified":false,"statuses_count":10591,"lang":"en","contributors_enabled":false,"is_translator":false,"is_translation_enabled":true,"profile_background_color":"EBEBEB","profile_background_image_url":"http://pbs.twimg.com/profile_background_images/11857640/NewSchools_PPT_Template_2008.png","profile_background_image_url_https":"https://pbs.twimg.com/profile_background_images/11857640/NewSchools_PPT_Template_2008.png","profile_background_tile":true,"profile_image_url":"http://pbs.twimg.com/profile_images/2620552226/ijbtx5ys15ve8hmb0039_normal.jpeg","profile_image_url_https":"https://pbs.twimg.com/profile_images/2620552226/ijbtx5ys15ve8hmb0039_normal.jpeg","profile_banner_url":"https://pbs.twimg.com/profile_banners/27247847/1399591760","profile_link_color":"FF7700","profile_sidebar_border_color":"5EB5E4","profile_sidebar_fill_color":"FFFFFF","profile_text_color":"636363","profile_use_background_image":false,"has_extended_profile":false,"default_profile":false,"default_profile_image":false,"following":null,"follow_request_sent":null,"notifications":null,"muting":null,"blocking":null,"blocked_by":null,"translator_type":"none"},{"id":1581289837,"id_str":"1581289837","name":"Malala Fund","screen_name":"MalalaFund","location":"RT do not equal endorsements","url":"http://Malala.org","description":"Malala Fund is working for a world where all girls can learn and lead without fear. Led by @Malala Yousafzai.","protected":false,"followers_count":616597,"friends_count":610,"listed_count":3358,"created_at":"Tue Jul 09 19:39:38 +0000 2013","favourites_count":11618,"utc_offset":-14400,"time_zone":"Eastern Time (US & Canada)","geo_enabled":false,"verified":true,"statuses_count":11032,"lang":"en","contributors_enabled":false,"is_translator":false,"is_translation_enabled":false,"profile_background_color":"C0DEED","profile_background_image_url":"http://pbs.twimg.com/profile_background_images/583706705927614465/2SQz16kT.png","profile_background_image_url_https":"https://pbs.twimg.com/profile_background_images/583706705927614465/2SQz16kT.png","profile_background_tile":false,"profile_image_url":"http://pbs.twimg.com/profile_images/649942098687365125/urESBy0O_normal.png","profile_image_url_https":"https://pbs.twimg.com/profile_images/649942098687365125/urESBy0O_normal.png","profile_banner_url":"https://pbs.twimg.com/profile_banners/1581289837/1519935209","profile_link_color":"FAB81E","profile_sidebar_border_color":"C0DEED","profile_sidebar_fill_color":"DDEEF6","profile_text_color":"333333","profile_use_background_image":true,"has_extended_profile":false,"default_profile":false,"default_profile_image":false,"following":null,"follow_request_sent":null,"notifications":null,"muting":null,"blocking":null,"blocked_by":null,"translator_type":"none"},{"id":793585473956425700,"id_str":"793585473956425728","name":"Breakthrough Energy","screen_name":"btenergy","location":"","url":"http://www.b-t.energy","description":"Breakthrough Energy invests in new technologies that make power reliable and affordable for everyone while not warming the planet.","protected":false,"followers_count":45483,"friends_count":56,"listed_count":312,"created_at":"Tue Nov 01 22:48:15 +0000 2016","favourites_count":33,"utc_offset":-25200,"time_zone":"Pacific Time (US & Canada)","geo_enabled":false,"verified":false,"statuses_count":204,"lang":"en","contributors_enabled":false,"is_translator":false,"is_translation_enabled":false,"profile_background_color":"F5F8FA","profile_background_image_url":null,"profile_background_image_url_https":null,"profile_background_tile":false,"profile_image_url":"http://pbs.twimg.com/profile_images/808098374817718272/0Tq7vo9f_normal.jpg","profile_image_url_https":"https://pbs.twimg.com/profile_images/808098374817718272/0Tq7vo9f_normal.jpg","profile_banner_url":"https://pbs.twimg.com/profile_banners/793585473956425728/1481500670","profile_link_color":"1DA1F2","profile_sidebar_border_color":"C0DEED","profile_sidebar_fill_color":"DDEEF6","profile_text_color":"333333","profile_use_background_image":true,"has_extended_profile":false,"default_profile":true,"default_profile_image":false,"following":null,"follow_request_sent":null,"notifications":null,"muting":null,"blocking":null,"blocked_by":null,"translator_type":"none"},{"id":18055737,"id_str":"18055737","name":"John Green","screen_name":"johngreen","location":"Indianapolis, IN","url":"http://johngreenbooks.com","description":"I am an author (The Fault in Our Stars, Turtles All the Way Down, etc.), YouTuber (vlogbrothers, crashcourse), and a person who does not cast movies.","protected":false,"followers_count":5419967,"friends_count":800,"listed_count":13779,"created_at":"Thu Dec 11 18:28:42 +0000 2008","favourites_count":13270,"utc_offset":-14400,"time_zone":"Eastern Time (US & Canada)","geo_enabled":true,"verified":true,"statuses_count":33582,"lang":"en","contributors_enabled":false,"is_translator":false,"is_translation_enabled":true,"profile_background_color":"00ADE2","profile_background_image_url":"http://abs.twimg.com/images/themes/theme14/bg.gif","profile_background_image_url_https":"https://abs.twimg.com/images/themes/theme14/bg.gif","profile_background_tile":false,"profile_image_url":"http://pbs.twimg.com/profile_images/942775513164136448/v7t45Wil_normal.jpg","profile_image_url_https":"https://pbs.twimg.com/profile_images/942775513164136448/v7t45Wil_normal.jpg","profile_banner_url":"https://pbs.twimg.com/profile_banners/18055737/1513704232","profile_link_color":"00ADE2","profile_sidebar_border_color":"FFFFFF","profile_sidebar_fill_color":"DDEEF6","profile_text_color":"333333","profile_use_background_image":false,"has_extended_profile":false,"default_profile":false,"default_profile_image":false,"following":null,"follow_request_sent":null,"notifications":null,"muting":null,"blocking":null,"blocked_by":null,"translator_type":"none"},{"id":15076390,"id_str":"15076390","name":"Padmasree","screen_name":"Padmasree","location":"California","url":"http://www.nio.io","description":"CEO @Nio_US Also love art, photography, Haiku and food :) Passionate about helping women in tech","protected":false,"followers_count":1643169,"friends_count":219,"listed_count":8196,"created_at":"Tue Jun 10 19:13:09 +0000 2008","favourites_count":1151,"utc_offset":-25200,"time_zone":"Pacific Time (US & Canada)","geo_enabled":true,"verified":true,"statuses_count":18507,"lang":"en","contributors_enabled":false,"is_translator":false,"is_translation_enabled":false,"profile_background_color":"BCDBDB","profile_background_image_url":"http://pbs.twimg.com/profile_background_images/124700386/DSCN1275_2.JPG","profile_background_image_url_https":"https://pbs.twimg.com/profile_background_images/124700386/DSCN1275_2.JPG","profile_background_tile":true,"profile_image_url":"http://pbs.twimg.com/profile_images/738429784/IMG_6843_2_normal.jpg","profile_image_url_https":"https://pbs.twimg.com/profile_images/738429784/IMG_6843_2_normal.jpg","profile_banner_url":"https://pbs.twimg.com/profile_banners/15076390/1430976413","profile_link_color":"0084B4","profile_sidebar_border_color":"FFFFFF","profile_sidebar_fill_color":"DDFFCC","profile_text_color":"333333","profile_use_background_image":true,"has_extended_profile":false,"default_profile":false,"default_profile_image":false,"following":null,"follow_request_sent":null,"notifications":null,"muting":null,"blocking":null,"blocked_by":null,"translator_type":"none"},{"id":76780096,"id_str":"76780096","name":"IHME at UW","screen_name":"IHME_UW","location":"Seattle, Washington","url":"http://healthdata.org","description":"The Institute for Health Metrics and Evaluation (IHME) is an independent research center at the University of Washington quantifying global health challenges.","protected":false,"followers_count":17340,"friends_count":2046,"listed_count":510,"created_at":"Wed Sep 23 22:41:25 +0000 2009","favourites_count":2263,"utc_offset":-25200,"time_zone":"Pacific Time (US & Canada)","geo_enabled":true,"verified":false,"statuses_count":11830,"lang":"en","contributors_enabled":false,"is_translator":false,"is_translation_enabled":false,"profile_background_color":"48AA43","profile_background_image_url":"http://pbs.twimg.com/profile_background_images/493808123535032320/aEscDuN5.jpeg","profile_background_image_url_https":"https://pbs.twimg.com/profile_background_images/493808123535032320/aEscDuN5.jpeg","profile_background_tile":false,"profile_image_url":"http://pbs.twimg.com/profile_images/509474832983920640/ijAkDalA_normal.png","profile_image_url_https":"https://pbs.twimg.com/profile_images/509474832983920640/ijAkDalA_normal.png","profile_banner_url":"https://pbs.twimg.com/profile_banners/76780096/1515015312","profile_link_color":"48AA43","profile_sidebar_border_color":"FFFFFF","profile_sidebar_fill_color":"DDEEF6","profile_text_color":"333333","profile_use_background_image":false,"has_extended_profile":false,"default_profile":false,"default_profile_image":false,"following":null,"follow_request_sent":null,"notifications":null,"muting":null,"blocking":null,"blocked_by":null,"translator_type":"none"},{"id":312266530,"id_str":"312266530","name":"Patrick McGee","screen_name":"PatrickMcGee_","location":"Deutschland","url":"http://www.ft.com","description":"Frankfurt Correspondent, @FT. Global Diplomacy grad student at @Soas, writing thesis on US military budget. Lazy runner striving for discipline.","protected":false,"followers_count":15134,"friends_count":2840,"listed_count":432,"created_at":"Mon Jun 06 21:04:18 +0000 2011","favourites_count":5294,"utc_offset":28800,"time_zone":"Hong Kong","geo_enabled":true,"verified":true,"statuses_count":23688,"lang":"en","contributors_enabled":false,"is_translator":false,"is_translation_enabled":false,"profile_background_color":"000000","profile_background_image_url":"http://abs.twimg.com/images/themes/theme15/bg.png","profile_background_image_url_https":"https://abs.twimg.com/images/themes/theme15/bg.png","profile_background_tile":false,"profile_image_url":"http://pbs.twimg.com/profile_images/855919324619567105/sbohhdB6_normal.jpg","profile_image_url_https":"https://pbs.twimg.com/profile_images/855919324619567105/sbohhdB6_normal.jpg","profile_banner_url":"https://pbs.twimg.com/profile_banners/312266530/1521746587","profile_link_color":"FF691F","profile_sidebar_border_color":"000000","profile_sidebar_fill_color":"000000","profile_text_color":"000000","profile_use_background_image":false,"has_extended_profile":false,"default_profile":false,"default_profile_image":false,"following":null,"follow_request_sent":null,"notifications":null,"muting":null,"blocking":null,"blocked_by":null,"translator_type":"none"},{"id":37710752,"id_str":"37710752","name":"Bill Nye","screen_name":"BillNye","location":"","url":"http://rodalebooks.com/billnye","description":"Bill Nye Saves the World Season 2, Part 1 now streaming on Netflix.","protected":false,"followers_count":5805755,"friends_count":112,"listed_count":21087,"created_at":"Mon May 04 17:42:04 +0000 2009","favourites_count":153,"utc_offset":-25200,"time_zone":"Pacific Time (US & Canada)","geo_enabled":true,"verified":true,"statuses_count":2048,"lang":"en","contributors_enabled":false,"is_translator":false,"is_translation_enabled":false,"profile_background_color":"001329","profile_background_image_url":"http://pbs.twimg.com/profile_background_images/156219911/space_005.jpg","profile_background_image_url_https":"https://pbs.twimg.com/profile_background_images/156219911/space_005.jpg","profile_background_tile":false,"profile_image_url":"http://pbs.twimg.com/profile_images/606232291438829568/8liw3txV_normal.jpg","profile_image_url_https":"https://pbs.twimg.com/profile_images/606232291438829568/8liw3txV_normal.jpg","profile_banner_url":"https://pbs.twimg.com/profile_banners/37710752/1514584552","profile_link_color":"ABB8C2","profile_sidebar_border_color":"2452A8","profile_sidebar_fill_color":"78A1CC","profile_text_color":"041317","profile_use_background_image":true,"has_extended_profile":false,"default_profile":false,"default_profile_image":false,"following":null,"follow_request_sent":null,"notifications":null,"muting":null,"blocking":null,"blocked_by":null,"translator_type":"none"},{"id":18839785,"id_str":"18839785","name":"Narendra Modi","screen_name":"narendramodi","location":"India","url":"http://www.narendramodi.in","description":"Prime Minister of India","protected":false,"followers_count":41705016,"friends_count":1938,"listed_count":22068,"created_at":"Sat Jan 10 17:18:56 +0000 2009","favourites_count":0,"utc_offset":19800,"time_zone":"New Delhi","geo_enabled":false,"verified":true,"statuses_count":18687,"lang":"en","contributors_enabled":false,"is_translator":false,"is_translation_enabled":false,"profile_background_color":"F4EDD4","profile_background_image_url":"http://pbs.twimg.com/profile_background_images/562185004696875009/DiiHx54g.jpeg","profile_background_image_url_https":"https://pbs.twimg.com/profile_background_images/562185004696875009/DiiHx54g.jpeg","profile_background_tile":false,"profile_image_url":"http://pbs.twimg.com/profile_images/718314968102367232/ypY1GPCQ_normal.jpg","profile_image_url_https":"https://pbs.twimg.com/profile_images/718314968102367232/ypY1GPCQ_normal.jpg","profile_banner_url":"https://pbs.twimg.com/profile_banners/18839785/1502777627","profile_link_color":"4E7096","profile_sidebar_border_color":"FFFFFF","profile_sidebar_fill_color":"D5DFED","profile_text_color":"233863","profile_use_background_image":true,"has_extended_profile":true,"default_profile":false,"default_profile_image":false,"following":null,"follow_request_sent":null,"notifications":null,"muting":null,"blocking":null,"blocked_by":null,"translator_type":"regular"}],"next_cursor":1479701347204708900,"next_cursor_str":"1479701347204708871","previous_cursor":0,"previous_cursor_str":"0"}